easysmi/__init__.py
easysmi/src/__init__.py
easysmi/src/main.py
easysmi/types/__init__.py
easysmi/types/type.py
easysmi-0.0.7.dist-info/METADATA
easysmi-0.0.7.dist-info/WHEEL
easysmi-0.0.7.dist-info/top_level.txt
easysmi-0.0.7.dist-info/RECORD
